<!-- Projects+ (Revan) -->
<Root>
	<Entry>
		<zType>TEXT_EFFECTCITY_PROJECT_MILITARY_TRAINING</zType>
		<English>Military Training</English>
	</Entry>
	<Entry>
		<zType>TEXT_EFFECTCITY_PROJECT_BUY_SLAVES</zType>
		<English>Bought Slaves</English>
	</Entry>
	<Entry>
		<zType>TEXT_EFFECTCITY_PROJECT_HOST_A_PLAY</zType>
		<English>Hosted a Play</English>
	</Entry>
	<Entry>
		<zType>TEXT_EFFECTCITY_PROJECT_RELIGION_YES</zType>
		<English>Supported Religion in this City</English>
	</Entry>
	<Entry>
		<zType>TEXT_EFFECTCITY_PROJECT_RELIGION_NO</zType>
		<English>Forbade Religion spread in this City</English>
	</Entry>
</Root>
